logs/__init__.py
logs/logs.py
tasks/__init__.py
tasks/main.py
tasks/main_gui.py
tasks/task.py
tasks/tasklist.py
tests/__init__.py
tests/test_task.py
tests/test_tasklist.py
my_task_manager-1.17.dist-info/METADATA
my_task_manager-1.17.dist-info/WHEEL
my_task_manager-1.17.dist-info/top_level.txt
my_task_manager-1.17.dist-info/RECORD
