Metadata-Version: 2.1
Name: my-task-manager
Version: 1.17
Summary: Métadonnées et informations sur la construction de projet To-do List
Author: Alban Pereira, Yuchen Xia, Aurélien Raulo, Salimatou Traore
Author-email: alban.pereira@telecom-paris.fr, yuchen.xia@telecom-paris.fr,         aurelien.raulo@telecom-paris.fr, salimatou.traore@telecom-paris.fr
Requires-Dist: datetime
Requires-Dist: logging
